nyangTest/test1.py
nyangTest/test2.py
nyangTest-0.0.0.2.dist-info/METADATA
nyangTest-0.0.0.2.dist-info/WHEEL
nyangTest-0.0.0.2.dist-info/top_level.txt
nyangTest-0.0.0.2.dist-info/RECORD
