Metadata-Version: 2.1
Name: nyangTest
Version: 0.0.0.2
Summary: My First Test Package
Home-page: https://blog.naver.com/gh5768
Author: Hyun Ho
Author-email: gh5768@hanmail.net
License: MIT
Platform: UNKNOWN
Requires-Python: >=3
